cohdl_yosys/__init__.py
cohdl_yosys/yosys.py
cohdl_yosys/yosys.pyi
cohdl_yosys/formal/__init__.py
cohdl_yosys/formal/_builtins.py
cohdl_yosys/formal/_builtins.pyi
cohdl_yosys/formal/_checker.py
cohdl_yosys/formal/_checker.pyi
cohdl_yosys/formal/_ctx_wrapper.py
cohdl_yosys/formal/_ctx_wrapper.pyi
cohdl_yosys/formal/_sequence.py
cohdl_yosys/formal/_sequence.pyi
cohdl_yosys-0.2.4.dist-info/licenses/LICENSE
cohdl_yosys-0.2.4.dist-info/METADATA
cohdl_yosys-0.2.4.dist-info/WHEEL
cohdl_yosys-0.2.4.dist-info/top_level.txt
cohdl_yosys-0.2.4.dist-info/RECORD
