Metadata-Version: 2.4
Name: cohdl_yosys
Version: 0.2.4
Summary: Formal verification support library for CoHDL
Author-email: Alexander Forster <alexander.forster123@gmail.com>
Project-URL: Homepage, https://github.com/alexander-forster/cohdl_yosys
Classifier: Programming Language :: Python :: 3
Classifier: License :: OSI Approved :: MIT License
Requires-Python: >=3.11
License-File: LICENSE
Requires-Dist: cohdl>=0.2.4
Dynamic: license-file
